KSSDS/T5_encoder.py
KSSDS/__init__.py
KSSDS/inference.py
KSSDS-1.0.6.dist-info/LICENSE
KSSDS-1.0.6.dist-info/METADATA
KSSDS-1.0.6.dist-info/WHEEL
KSSDS-1.0.6.dist-info/top_level.txt
KSSDS-1.0.6.dist-info/RECORD
