Metadata-Version: 2.1
Name: KSSDS
Version: 1.0.6
Summary: Korean Sentence Splitter for Dialogue Systems
Home-page: https://github.com/ggomarobot/KSSDS
Author: Gun Yang
Author-email: ggomarobot@gmail.com
License: MIT
Keywords: Korean NLP sentence splitter dialogue systems
Classifier: Programming Language :: Python :: 3
Classifier: Programming Language :: Python :: 3.8
Classifier: Programming Language :: Python :: 3.9
Classifier: Programming Language :: Python :: 3.10
Classifier: Programming Language :: Python :: 3.11
Classifier: Programming Language :: Python :: 3.12
Classifier: License :: OSI Approved :: MIT License
Classifier: Operating System :: OS Independent
Requires-Python: >=3.8
License-File: LICENSE
Requires-Dist: GPUtil <2.0,>=1.4
Requires-Dist: numpy <2.0,>=1.19.5
Requires-Dist: PyYAML <7.0,>=6.0
Requires-Dist: scikit-learn <2.0,>=1.6
Requires-Dist: torch <3.0,>=2.5
Requires-Dist: transformers <5.0,>=4.42
